load/__init__.py
load-2019.4.1.dist-info/METADATA
load-2019.4.1.dist-info/WHEEL
load-2019.4.1.dist-info/top_level.txt
load-2019.4.1.dist-info/RECORD
